itkwasm_transform_io_wasi/__init__.py
itkwasm_transform_io_wasi/_version.py
itkwasm_transform_io_wasi/extension_to_transform_io.py
itkwasm_transform_io_wasi/hdf5_read_transform.py
itkwasm_transform_io_wasi/hdf5_write_transform.py
itkwasm_transform_io_wasi/mat_read_transform.py
itkwasm_transform_io_wasi/mat_write_transform.py
itkwasm_transform_io_wasi/mnc_read_transform.py
itkwasm_transform_io_wasi/mnc_write_transform.py
itkwasm_transform_io_wasi/read_transform.py
itkwasm_transform_io_wasi/transform_io_index.py
itkwasm_transform_io_wasi/txt_read_transform.py
itkwasm_transform_io_wasi/txt_write_transform.py
itkwasm_transform_io_wasi/wasm_read_transform.py
itkwasm_transform_io_wasi/wasm_write_transform.py
itkwasm_transform_io_wasi/wasm_zstd_read_transform.py
itkwasm_transform_io_wasi/wasm_zstd_write_transform.py
itkwasm_transform_io_wasi/write_transform.py
itkwasm_transform_io_wasi/wasm_modules/hdf5-read-transform.wasi.wasm
itkwasm_transform_io_wasi/wasm_modules/hdf5-write-transform.wasi.wasm
itkwasm_transform_io_wasi/wasm_modules/mat-read-transform.wasi.wasm
itkwasm_transform_io_wasi/wasm_modules/mat-write-transform.wasi.wasm
itkwasm_transform_io_wasi/wasm_modules/mnc-read-transform.wasi.wasm
itkwasm_transform_io_wasi/wasm_modules/mnc-write-transform.wasi.wasm
itkwasm_transform_io_wasi/wasm_modules/txt-read-transform.wasi.wasm
itkwasm_transform_io_wasi/wasm_modules/txt-write-transform.wasi.wasm
itkwasm_transform_io_wasi/wasm_modules/wasm-read-transform.wasi.wasm
itkwasm_transform_io_wasi/wasm_modules/wasm-write-transform.wasi.wasm
itkwasm_transform_io_wasi/wasm_modules/wasm-zstd-read-transform.wasi.wasm
itkwasm_transform_io_wasi/wasm_modules/wasm-zstd-write-transform.wasi.wasm
itkwasm_transform_io_wasi-1.1.0.dist-info/METADATA
itkwasm_transform_io_wasi-1.1.0.dist-info/WHEEL
itkwasm_transform_io_wasi-1.1.0.dist-info/RECORD
